oni_api/__init__.py
oni_api/crowdtangle.py
oni_api/spotify.py
oni_api/youtube.py
oni_api-1.0.11.dist-info/LICENSE
oni_api-1.0.11.dist-info/METADATA
oni_api-1.0.11.dist-info/WHEEL
oni_api-1.0.11.dist-info/top_level.txt
oni_api-1.0.11.dist-info/RECORD
