Metadata-Version: 2.1
Name: oni-api
Version: 1.0.11
Summary: Helper para consumo de APIs
Home-page: https://github.com/LucasHeilbuth
Download-URL: https://github.com/Onimusic/oni_api_helper.git
Author: Lucas Heilbuth Nazareth de Sousa
Author-email: lucasheilbuth@yahoo.com.br
Keywords: onimusic
Classifier: Programming Language :: Python :: 3
Classifier: License :: OSI Approved :: MIT License
Classifier: Operating System :: OS Independent
License-File: LICENSE
Requires-Dist: cachetools
Requires-Dist: certifi
Requires-Dist: charset-normalizer
Requires-Dist: google-api-core
Requires-Dist: google-api-python-client
Requires-Dist: google-auth
Requires-Dist: google-auth-httplib2
Requires-Dist: googleapis-common-protos
Requires-Dist: httplib2
Requires-Dist: idna
Requires-Dist: numpy
Requires-Dist: pandas
Requires-Dist: protobuf
Requires-Dist: pyasn1
Requires-Dist: pyasn1-modules
Requires-Dist: pyparsing
Requires-Dist: python-dateutil
Requires-Dist: pytz
Requires-Dist: requests
Requires-Dist: rsa
Requires-Dist: six
Requires-Dist: uritemplate
Requires-Dist: urllib3
